{
  "nodes": {
    "SitePage /dev-404-page/": {
      "layout": "index",
      "jsonName": "dev-404-page.json",
      "internalComponentName": "ComponentDev404Page",
      "path": "/dev-404-page/",
      "component": "/Users/edgarchaparro/code/my-react-app/.cache/dev-404-page.js",
      "componentChunkName": "component---cache-dev-404-page-js",
      "context": {},
      "pluginCreator___NODE": "Plugin dev-404-page",
      "pluginCreatorId": "Plugin dev-404-page",
      "componentPath": "/Users/edgarchaparro/code/my-react-app/.cache/dev-404-page.js",
      "id": "SitePage /dev-404-page/",
      "parent": "SOURCE",
      "children": [],
      "internal": {
        "type": "SitePage",
        "contentDigest": "846afdb7c40fdd14553953cef4d075ad",
        "description": "Plugin dev-404-page",
        "owner": "internal-data-bridge"
      }
    },
    "Plugin dev-404-page": {
      "resolve": "/Users/edgarchaparro/code/my-react-app/node_modules/gatsby/dist/internal-plugins/dev-404-page",
      "id": "Plugin dev-404-page",
      "name": "dev-404-page",
      "version": "1.0.0",
      "pluginOptions": {
        "plugins": []
      },
      "nodeAPIs": [
        "createPagesStatefully"
      ],
      "browserAPIs": [],
      "ssrAPIs": [],
      "pluginFilepath": "/Users/edgarchaparro/code/my-react-app/node_modules/gatsby/dist/internal-plugins/dev-404-page",
      "packageJson": {
        "name": "dev-404-page",
        "description": "Internal plugin to add a 404 page in development with helpful information",
        "version": "1.0.0",
        "main": "index.js",
        "author": "Kyle Mathews <mathews.kyle@gmail.com>",
        "license": "MIT",
        "dependencies": [],
        "devDependencies": [],
        "peerDependencies": [],
        "optionalDependecies": [],
        "bundledDependecies": []
      },
      "parent": "SOURCE",
      "children": [],
      "internal": {
        "contentDigest": "dfc12b46e79786eabfc5bc056b64ec40",
        "type": "SitePlugin",
        "owner": "internal-data-bridge"
      }
    },
    "Plugin component-page-creator": {
      "resolve": "/Users/edgarchaparro/code/my-react-app/node_modules/gatsby/dist/internal-plugins/component-page-creator",
      "id": "Plugin component-page-creator",
      "name": "component-page-creator",
      "version": "1.0.0",
      "pluginOptions": {
        "plugins": []
      },
      "nodeAPIs": [
        "createPagesStatefully"
      ],
      "browserAPIs": [],
      "ssrAPIs": [],
      "pluginFilepath": "/Users/edgarchaparro/code/my-react-app/node_modules/gatsby/dist/internal-plugins/component-page-creator",
      "packageJson": {
        "name": "component-page-creator",
        "description": "An internal Gatsby plugin that creates pages from component files in src/pages",
        "version": "1.0.0",
        "main": "index.js",
        "keywords": [
          "gatsby",
          "gatsby-plugin"
        ],
        "author": "Kyle Mathews <mathews.kyle@gmail.com>",
        "license": "MIT",
        "dependencies": [],
        "devDependencies": [],
        "peerDependencies": [],
        "optionalDependecies": [],
        "bundledDependecies": []
      },
      "parent": "SOURCE",
      "children": [],
      "internal": {
        "contentDigest": "de9c217521bf352799c23b02f5696dd9",
        "type": "SitePlugin",
        "owner": "internal-data-bridge"
      }
    },
    "Plugin component-layout-creator": {
      "resolve": "/Users/edgarchaparro/code/my-react-app/node_modules/gatsby/dist/internal-plugins/component-layout-creator",
      "id": "Plugin component-layout-creator",
      "name": "component-layout-creator",
      "version": "1.0.0",
      "pluginOptions": {
        "plugins": []
      },
      "nodeAPIs": [
        "createLayouts"
      ],
      "browserAPIs": [],
      "ssrAPIs": [],
      "pluginFilepath": "/Users/edgarchaparro/code/my-react-app/node_modules/gatsby/dist/internal-plugins/component-layout-creator",
      "packageJson": {
        "name": "component-layout-creator",
        "description": "An internal Gatsby plugin that creates pages from component files in src/layouts",
        "version": "1.0.0",
        "main": "index.js",
        "keywords": [
          "gatsby",
          "gatsby-plugin"
        ],
        "author": "Kyle Mathews <mathews.kyle@gmail.com>",
        "license": "MIT",
        "dependencies": [],
        "devDependencies": [],
        "peerDependencies": [],
        "optionalDependecies": [],
        "bundledDependecies": []
      },
      "parent": "SOURCE",
      "children": [],
      "internal": {
        "contentDigest": "53a5f4e1fd4788f8489bfbea6ef1e7b4",
        "type": "SitePlugin",
        "owner": "internal-data-bridge"
      }
    },
    "Plugin internal-data-bridge": {
      "resolve": "/Users/edgarchaparro/code/my-react-app/node_modules/gatsby/dist/internal-plugins/internal-data-bridge",
      "id": "Plugin internal-data-bridge",
      "name": "internal-data-bridge",
      "version": "1.0.0",
      "pluginOptions": {
        "plugins": []
      },
      "nodeAPIs": [
        "sourceNodes",
        "onCreatePage"
      ],
      "browserAPIs": [],
      "ssrAPIs": [],
      "pluginFilepath": "/Users/edgarchaparro/code/my-react-app/node_modules/gatsby/dist/internal-plugins/internal-data-bridge",
      "packageJson": {
        "name": "internal-data-bridge",
        "description": "An internal Gatsby plugin which creates data nodes from internal data",
        "version": "1.0.0",
        "main": "index.js",
        "author": "Kyle Mathews <mathews.kyle@gmail.com>",
        "license": "MIT",
        "dependencies": [],
        "devDependencies": [],
        "peerDependencies": [],
        "optionalDependecies": [],
        "bundledDependecies": []
      },
      "parent": "SOURCE",
      "children": [],
      "internal": {
        "contentDigest": "5784c16bc86a4b0ae2fe578ed19b3b1f",
        "type": "SitePlugin",
        "owner": "internal-data-bridge"
      }
    },
    "Plugin prod-404": {
      "resolve": "/Users/edgarchaparro/code/my-react-app/node_modules/gatsby/dist/internal-plugins/prod-404",
      "id": "Plugin prod-404",
      "name": "prod-404",
      "version": "1.0.0",
      "pluginOptions": {
        "plugins": []
      },
      "nodeAPIs": [
        "onCreatePage"
      ],
      "browserAPIs": [],
      "ssrAPIs": [],
      "pluginFilepath": "/Users/edgarchaparro/code/my-react-app/node_modules/gatsby/dist/internal-plugins/prod-404",
      "packageJson": {
        "name": "prod-404",
        "description": "Internal plugin to detect various flavors of 404 pages and ensure there's a 404.html path created as well to ensure compatability with static hosts",
        "version": "1.0.0",
        "main": "index.js",
        "author": "Kyle Mathews <mathews.kyle@gmail.com>",
        "license": "MIT",
        "dependencies": [],
        "devDependencies": [],
        "peerDependencies": [],
        "optionalDependecies": [],
        "bundledDependecies": []
      },
      "parent": "SOURCE",
      "children": [],
      "internal": {
        "contentDigest": "32858d99b89665ff23f2698b1c4383af",
        "type": "SitePlugin",
        "owner": "internal-data-bridge"
      }
    },
    "Plugin query-runner": {
      "resolve": "/Users/edgarchaparro/code/my-react-app/node_modules/gatsby/dist/internal-plugins/query-runner",
      "id": "Plugin query-runner",
      "name": "query-runner",
      "version": "1.0.0",
      "pluginOptions": {
        "plugins": []
      },
      "nodeAPIs": [
        "onCreatePage",
        "onCreateLayout"
      ],
      "browserAPIs": [],
      "ssrAPIs": [],
      "pluginFilepath": "/Users/edgarchaparro/code/my-react-app/node_modules/gatsby/dist/internal-plugins/query-runner",
      "packageJson": {
        "name": "query-runner",
        "description": "Internal plugin for running queries",
        "version": "1.0.0",
        "main": "index.js",
        "author": "",
        "license": "MIT",
        "dependencies": [],
        "devDependencies": [],
        "peerDependencies": [],
        "optionalDependecies": [],
        "bundledDependecies": []
      },
      "parent": "SOURCE",
      "children": [],
      "internal": {
        "contentDigest": "df3e52f19eab3aa70c61e9a0f4d5c320",
        "type": "SitePlugin",
        "owner": "internal-data-bridge"
      }
    },
    "Plugin gatsby-plugin-react-helmet": {
      "resolve": "/Users/edgarchaparro/code/my-react-app/node_modules/gatsby-plugin-react-helmet",
      "id": "Plugin gatsby-plugin-react-helmet",
      "name": "gatsby-plugin-react-helmet",
      "version": "2.0.10",
      "pluginOptions": {
        "plugins": []
      },
      "nodeAPIs": [],
      "browserAPIs": [],
      "ssrAPIs": [
        "onRenderBody"
      ],
      "pluginFilepath": "/Users/edgarchaparro/code/my-react-app/node_modules/gatsby-plugin-react-helmet",
      "packageJson": {
        "name": "gatsby-plugin-react-helmet",
        "description": "Manage document head data with react-helmet. Provides drop-in server rendering support for Gatsby.",
        "version": "2.0.10",
        "main": "index.js",
        "keywords": [
          "gatsby",
          "gatsby-plugin",
          "favicon",
          "react-helmet",
          "seo",
          "document",
          "head",
          "title",
          "meta",
          "link",
          "script",
          "base",
          "noscript",
          "style"
        ],
        "author": {
          "name": "Kyle Mathews",
          "email": "matthews.kyle@gmail.com"
        },
        "license": "MIT",
        "dependencies": [
          {
            "name": "babel-runtime",
            "version": "^6.26.0"
          }
        ],
        "devDependencies": [
          {
            "name": "babel-cli",
            "version": "^6.26.0"
          },
          {
            "name": "cross-env",
            "version": "^5.0.5"
          }
        ],
        "peerDependencies": [
          {
            "name": "gatsby",
            "version": "^1.0.0"
          },
          {
            "name": "react-helmet",
            "version": ">=5.1.3"
          }
        ],
        "optionalDependecies": [],
        "bundledDependecies": []
      },
      "parent": "SOURCE",
      "children": [],
      "internal": {
        "contentDigest": "5afddaefa4623c3c6a10c5fd84e061c9",
        "type": "SitePlugin",
        "owner": "internal-data-bridge"
      }
    },
    "Plugin gatsby-source-contentful": {
      "resolve": "/Users/edgarchaparro/code/my-react-app/node_modules/gatsby-source-contentful",
      "id": "Plugin gatsby-source-contentful",
      "name": "gatsby-source-contentful",
      "version": "1.3.54",
      "pluginOptions": {
        "plugins": [],
        "spaceId": "5i1yx4uz4yke",
        "accessToken": "d3dcefa66ab23ebee326479f9f7d25818e59fac9440b37e9336c1f052fef9e3f"
      },
      "nodeAPIs": [
        "setFieldsOnGraphQLNodeType",
        "sourceNodes",
        "onPreBootstrap",
        "onPreExtractQueries"
      ],
      "browserAPIs": [],
      "ssrAPIs": [],
      "pluginFilepath": "/Users/edgarchaparro/code/my-react-app/node_modules/gatsby-source-contentful",
      "packageJson": {
        "name": "gatsby-source-contentful",
        "description": "Gatsby source plugin for building websites using the Contentful CMS as a data source",
        "version": "1.3.54",
        "keywords": [
          "gatsby",
          "gatsby-plugin",
          "gatsby-source-plugin"
        ],
        "author": {
          "name": "Marcus Ericsson",
          "email": "mericsson@gmail.com",
          "url": "mericsson.com"
        },
        "license": "MIT",
        "dependencies": [
          {
            "name": "axios",
            "version": "^0.16.2"
          },
          {
            "name": "babel-runtime",
            "version": "^6.26.0"
          },
          {
            "name": "base64-img",
            "version": "^1.0.3"
          },
          {
            "name": "bluebird",
            "version": "^3.5.0"
          },
          {
            "name": "contentful",
            "version": "^6.1.0"
          },
          {
            "name": "deep-map",
            "version": "^1.5.0"
          },
          {
            "name": "fs-extra",
            "version": "^4.0.2"
          },
          {
            "name": "gatsby-plugin-sharp",
            "version": "^1.6.48"
          },
          {
            "name": "json-stringify-safe",
            "version": "^5.0.1"
          },
          {
            "name": "lodash",
            "version": "^4.17.4"
          },
          {
            "name": "qs",
            "version": "^6.4.0"
          }
        ],
        "devDependencies": [
          {
            "name": "cross-env",
            "version": "^5.0.5"
          }
        ],
        "peerDependencies": [],
        "optionalDependecies": [],
        "bundledDependecies": []
      },
      "parent": "SOURCE",
      "children": [],
      "internal": {
        "contentDigest": "1b2fb9223277e20551d870646e223fd4",
        "type": "SitePlugin",
        "owner": "internal-data-bridge"
      }
    },
    "Plugin default-site-plugin": {
      "resolve": "/Users/edgarchaparro/code/my-react-app",
      "id": "Plugin default-site-plugin",
      "name": "default-site-plugin",
      "version": "e9ca8a12a3952b80591ae4fafa589741",
      "pluginOptions": {
        "plugins": []
      },
      "nodeAPIs": [],
      "browserAPIs": [],
      "ssrAPIs": [],
      "pluginFilepath": "/Users/edgarchaparro/code/my-react-app",
      "packageJson": {
        "name": "gatsby-starter-default",
        "description": "Gatsby default starter",
        "version": "1.0.0",
        "keywords": [
          "gatsby"
        ],
        "author": "Kyle Mathews <mathews.kyle@gmail.com>",
        "license": "MIT",
        "dependencies": [
          {
            "name": "gatsby",
            "version": "^1.9.247"
          },
          {
            "name": "gatsby-link",
            "version": "^1.6.40"
          },
          {
            "name": "gatsby-plugin-react-helmet",
            "version": "^2.0.10"
          },
          {
            "name": "gatsby-source-contentful",
            "version": "^1.3.54"
          },
          {
            "name": "react-helmet",
            "version": "^5.2.0"
          },
          {
            "name": "react-stripe-checkout",
            "version": "^2.6.3"
          },
          {
            "name": "stripe",
            "version": "^6.4.0"
          },
          {
            "name": "styled-components",
            "version": "^3.3.3"
          }
        ],
        "devDependencies": [
          {
            "name": "prettier",
            "version": "^1.12.0"
          }
        ],
        "peerDependencies": [],
        "optionalDependecies": [],
        "bundledDependecies": []
      },
      "parent": "SOURCE",
      "children": [],
      "internal": {
        "contentDigest": "00ad9a79456290c95e5a7a9f2c7a1355",
        "type": "SitePlugin",
        "owner": "internal-data-bridge"
      }
    },
    "Site": {
      "siteMetadata": {
        "title": "Design+Code 3",
        "description": "Complete courses about the best tools and design systems. Prototype and build apps with React and Swift. 60 hours of video content and resource materials. No coding experience required.",
        "keywords": "react course, react for designers, ios development, sketch app, swift app course, arkit 2, after effects, create sketch plugin"
      },
      "port": "8000",
      "host": "localhost",
      "pathPrefix": "",
      "polyfill": true,
      "buildTime": "2018-07-28T23:55:33.769Z",
      "id": "Site",
      "parent": "SOURCE",
      "children": [],
      "internal": {
        "contentDigest": "c7445548bf258cd9fbbf5a162d89934c",
        "type": "Site",
        "owner": "internal-data-bridge"
      }
    },
    "Link": {
      "id": "Link",
      "parent": null,
      "children": [],
      "name": "Link",
      "displayField": "title",
      "description": "",
      "internal": {
        "type": "ContentfulContentType",
        "contentDigest": "4d6413a6137bc10d2af222f0161c189a",
        "owner": "gatsby-source-contentful"
      }
    },
    "c62bhWSged2WaC6MQGI42yW": {
      "title": "Workshops",
      "url": "/workshops",
      "id": "c62bhWSged2WaC6MQGI42yW",
      "contentful_id": "62bhWSged2WaC6MQGI42yW",
      "createdAt": "2018-07-28T21:40:32.599Z",
      "updatedAt": "2018-07-28T21:40:32.599Z",
      "parent": "Link",
      "children": [],
      "internal": {
        "type": "ContentfulLink",
        "contentDigest": "4b9bc2fd280a4094885e2c7d044b7c27",
        "owner": "gatsby-source-contentful"
      },
      "node_locale": "en-US"
    },
    "c4Ag3D8piXS6ogEoYEa6M2c": {
      "title": "Downloads",
      "url": "/downloads",
      "id": "c4Ag3D8piXS6ogEoYEa6M2c",
      "contentful_id": "4Ag3D8piXS6ogEoYEa6M2c",
      "createdAt": "2018-07-28T21:40:21.269Z",
      "updatedAt": "2018-07-28T21:40:21.269Z",
      "parent": "Link",
      "children": [],
      "internal": {
        "type": "ContentfulLink",
        "contentDigest": "57ef16c4ceaf0969a2c288e75bdaeb52",
        "owner": "gatsby-source-contentful"
      },
      "node_locale": "en-US"
    },
    "c1KnmL3KR7CoCQe2ssyeWEy": {
      "title": "Courses",
      "url": "/courses",
      "id": "c1KnmL3KR7CoCQe2ssyeWEy",
      "contentful_id": "1KnmL3KR7CoCQe2ssyeWEy",
      "createdAt": "2018-07-28T21:40:01.566Z",
      "updatedAt": "2018-07-28T21:40:01.566Z",
      "parent": "Link",
      "children": [],
      "internal": {
        "type": "ContentfulLink",
        "contentDigest": "3e96e8c24e0243c3f33a216b2f936d2d",
        "owner": "gatsby-source-contentful"
      },
      "node_locale": "en-US"
    },
    "c1nLSmTl2V66mYGAuMqIoa4": {
      "title": "Home",
      "url": "/",
      "id": "c1nLSmTl2V66mYGAuMqIoa4",
      "contentful_id": "1nLSmTl2V66mYGAuMqIoa4",
      "createdAt": "2018-07-28T21:37:56.911Z",
      "updatedAt": "2018-07-28T21:37:56.911Z",
      "parent": "Link",
      "children": [],
      "internal": {
        "type": "ContentfulLink",
        "contentDigest": "cf23c57cc9b3cd0efcd8d1d09545041f",
        "owner": "gatsby-source-contentful"
      },
      "node_locale": "en-US"
    },
    "SitePage /404/": {
      "layout": "index",
      "jsonName": "404.json",
      "internalComponentName": "Component404",
      "path": "/404/",
      "component": "/Users/edgarchaparro/code/my-react-app/src/pages/404.js",
      "componentChunkName": "component---src-pages-404-js",
      "context": {},
      "pluginCreator___NODE": "Plugin component-page-creator",
      "pluginCreatorId": "Plugin component-page-creator",
      "componentPath": "/Users/edgarchaparro/code/my-react-app/src/pages/404.js",
      "id": "SitePage /404/",
      "parent": "SOURCE",
      "children": [],
      "internal": {
        "type": "SitePage",
        "contentDigest": "0e3dcce479a7771d8989a2f025c466d6",
        "description": "Plugin component-page-creator",
        "owner": "internal-data-bridge"
      }
    },
    "SitePage /": {
      "layout": "index",
      "jsonName": "index.json",
      "internalComponentName": "ComponentIndex",
      "path": "/",
      "component": "/Users/edgarchaparro/code/my-react-app/src/pages/index.js",
      "componentChunkName": "component---src-pages-index-js",
      "context": {},
      "pluginCreator___NODE": "Plugin component-page-creator",
      "pluginCreatorId": "Plugin component-page-creator",
      "componentPath": "/Users/edgarchaparro/code/my-react-app/src/pages/index.js",
      "id": "SitePage /",
      "parent": "SOURCE",
      "children": [],
      "internal": {
        "type": "SitePage",
        "contentDigest": "1a8ae311d598ebd12bd258ead67fddfd",
        "description": "Plugin component-page-creator",
        "owner": "internal-data-bridge"
      }
    },
    "SitePage /page-2/": {
      "layout": "index",
      "jsonName": "page-2.json",
      "internalComponentName": "ComponentPage2",
      "path": "/page-2/",
      "component": "/Users/edgarchaparro/code/my-react-app/src/pages/page-2.js",
      "componentChunkName": "component---src-pages-page-2-js",
      "context": {},
      "pluginCreator___NODE": "Plugin component-page-creator",
      "pluginCreatorId": "Plugin component-page-creator",
      "componentPath": "/Users/edgarchaparro/code/my-react-app/src/pages/page-2.js",
      "id": "SitePage /page-2/",
      "parent": "SOURCE",
      "children": [],
      "internal": {
        "type": "SitePage",
        "contentDigest": "3b11ad628a8532446fbee531610ba2b4",
        "description": "Plugin component-page-creator",
        "owner": "internal-data-bridge"
      }
    },
    "SitePage /404.html": {
      "layout": "index",
      "jsonName": "404-html.json",
      "internalComponentName": "Component404Html",
      "path": "/404.html",
      "component": "/Users/edgarchaparro/code/my-react-app/src/pages/404.js",
      "componentChunkName": "component---src-pages-404-js",
      "context": {},
      "pluginCreator___NODE": "Plugin prod-404",
      "pluginCreatorId": "Plugin prod-404",
      "componentPath": "/Users/edgarchaparro/code/my-react-app/src/pages/404.js",
      "id": "SitePage /404.html",
      "parent": "SOURCE",
      "children": [],
      "internal": {
        "type": "SitePage",
        "contentDigest": "596fbc47ba7d1cf70e7c8a01df16acb7",
        "description": "Plugin prod-404",
        "owner": "internal-data-bridge"
      }
    }
  },
  "status": {
    "plugins": {
      "gatsby-source-contentful": {
        "5i1yx4uz4yke-master": "w5ZGw6JFwqZmVcKsE8Kow4grw45QdybDisKoa2_CnzMIwqvDqsKhFEDCjlp4EF3DkyEZelzDkMK_w5EKFgwcwp5JwqxlRS1Ww6QobjDCih3CosObw5sewrbCn8KSGT3CiTMHLcKsK0EAw71rW8OPw6w"
      }
    },
    "PLUGINS_HASH": "a18fccc7ac6a6dbd9536795fe9fc54f9"
  },
  "componentDataDependencies": {
    "nodes": {
      "Site": [
        "LAYOUT___index"
      ]
    },
    "connections": {
      "SitePage": [
        "/dev-404-page/"
      ],
      "ContentfulLink": [
        "LAYOUT___index"
      ]
    }
  }
}